{"assets":[{"id":"13","layers":[{"ind":12,"ty":4,"parent":11,"ks":{},"ip":0,"op":241,"st":0,"shapes":[{"ty":"rc","p":{"a":1,"k":[{"t":0,"s":[0,0],"i":{"x":[1,1],"y":[1,1]},"o":{"x":[0,0],"y":[0,0]}},{"t":45,"s":[0,0],"i":{"x":[0.741,0.741],"y":[0.482,0.482]},"o":{"x":[0.4,0.4],"y":[0,0]}},{"t":66.96,"s":[45.499,7],"i":{"x":[0.679,0.679],"y":[0.999,0.999]},"o":{"x":[0.347,0.347],"y":[0.693,0.693]}},{"t":77.94,"s":[34.112,5.248],"i":{"x":[0.733,0.733],"y":[0.466,0.466]},"o":{"x":[0.394,0.394],"y":[0.001,0.001]}},{"t":88.926,"s":[45.5,7],"i":{"x":[0.608,0.608],"y":[0.998,0.998]},"o":{"x":[0.27,0.27],"y":[0.539,0.539]}},{"t":94.422,"s":[42.647,6.561],"i":{"x":[0.564,0.564],"y":[0.129,0.129]},"o":{"x":[0.214,0.214],"y":[0.001,0.001]}},{"t":99.918,"s":[45.498,7],"i":{"x":[0.583,0.583],"y":[0.998,0.998]},"o":{"x":[0.236,0.236],"y":[0.473,0.473]}},{"t":102.678,"s":[44.783,6.89],"i":{"x":[0.533,0.533],"y":[0.07,0.07]},"o":{"x":[0.17,0.17],"y":[0.002,0.002]}},{"t":105.432,"s":[45.499,7],"i":{"x":[0.971,0.971],"y":[1,1]},"o":{"x":[0.539,0.539],"y":[1,1]}},{"t":106.818,"s":[45.319,6.972],"i":{"x":[0.454,0.454],"y":[0,0]},"o":{"x":[0.011,0.011],"y":[0,0]}},{"t":108.204,"s":[45.5,7],"i":{"x":[1,1],"y":[1,1]},"o":{"x":[0,0],"y":[0,0]}},{"t":108.9,"s":[45.454,6.993],"i":{"x":[1,1],"y":[1,1]},"o":{"x":[0,0],"y":[0,0]}},{"t":109.602,"s":[45.5,7],"i":{"x":[1,1],"y":[1,1]},"o":{"x":[0,0],"y":[0,0]}},{"t":240,"s":[45.5,7],"h":1}]},"r":{"a":0,"k":0},"s":{"a":1,"k":[{"t":0,"s":[0,0],"i":{"x":[1,1],"y":[1,1]},"o":{"x":[0,0],"y":[0,0]}},{"t":45,"s":[0,0],"i":{"x":[0.741,0.741],"y":[0.482,0.482]},"o":{"x":[0.4,0.4],"y":[0,0]}},{"t":66.96,"s":[90.998,14],"i":{"x":[0.679,0.679],"y":[0.999,0.999]},"o":{"x":[0.347,0.347],"y":[0.693,0.693]}},{"t":77.94,"s":[68.224,10.496],"i":{"x":[0.733,0.733],"y":[0.466,0.466]},"o":{"x":[0.394,0.394],"y":[0.001,0.001]}},{"t":88.926,"s":[90.999,14],"i":{"x":[0.608,0.608],"y":[0.998,0.998]},"o":{"x":[0.27,0.27],"y":[0.539,0.539]}},{"t":94.422,"s":[85.293,13.122],"i":{"x":[0.564,0.564],"y":[0.129,0.129]},"o":{"x":[0.214,0.214],"y":[0.001,0.001]}},{"t":99.918,"s":[90.996,13.999],"i":{"x":[0.583,0.583],"y":[0.998,0.998]},"o":{"x":[0.236,0.236],"y":[0.473,0.473]}},{"t":102.678,"s":[89.566,13.779],"i":{"x":[0.533,0.533],"y":[0.07,0.07]},"o":{"x":[0.17,0.17],"y":[0.002,0.002]}},{"t":105.432,"s":[90.997,14],"i":{"x":[0.971,0.971],"y":[1,1]},"o":{"x":[0.539,0.539],"y":[1,1]}},{"t":106.818,"s":[90.637,13.944],"i":{"x":[0.454,0.454],"y":[0,0]},"o":{"x":[0.011,0.011],"y":[0,0]}},{"t":108.204,"s":[90.999,14],"i":{"x":[1,1],"y":[1,1]},"o":{"x":[0,0],"y":[0,0]}},{"t":108.9,"s":[90.907,13.986],"i":{"x":[1,1],"y":[1,1]},"o":{"x":[0,0],"y":[0,0]}},{"t":109.602,"s":[91,14],"i":{"x":[1,1],"y":[1,1]},"o":{"x":[0,0],"y":[0,0]}},{"t":240,"s":[91,14],"h":1}]}},{"ty":"fl","c":{"a":0,"k":[0,0,0]},"o":{"a":0,"k":100}}]},{"ind":11,"ty":3,"parent":10,"ks":{"p":{"a":1,"k":[{"t":0,"s":[91,0],"i":{"x":[1,1],"y":[1,1]},"o":{"x":[0,0],"y":[0,0]}},{"t":45,"s":[91,0],"i":{"x":[0.741,1],"y":[0.482,1]},"o":{"x":[0.4,0],"y":[0,0]}},{"t":66.96,"s":[0.002,0],"i":{"x":[0.679,1],"y":[0.999,1]},"o":{"x":[0.347,0],"y":[0.693,0]}},{"t":77.94,"s":[22.776,0],"i":{"x":[0.733,1],"y":[0.466,1]},"o":{"x":[0.394,0],"y":[0.001,0]}},{"t":88.926,"s":[0.001,0],"i":{"x":[0.608,1],"y":[0.998,1]},"o":{"x":[0.27,0],"y":[0.539,0]}},{"t":94.422,"s":[5.707,0],"i":{"x":[0.564,1],"y":[0.129,1]},"o":{"x":[0.214,0],"y":[0.001,0]}},{"t":99.918,"s":[0.004,0],"i":{"x":[0.583,1],"y":[0.998,1]},"o":{"x":[0.236,0],"y":[0.473,0]}},{"t":102.678,"s":[1.434,0],"i":{"x":[0.533,1],"y":[0.07,1]},"o":{"x":[0.17,0],"y":[0.002,0]}},{"t":105.432,"s":[0.003,0],"i":{"x":[0.971,1],"y":[1,1]},"o":{"x":[0.539,0],"y":[1,0]}},{"t":106.818,"s":[0.363,0],"i":{"x":[0.454,1],"y":[0,1]},"o":{"x":[0.011,0],"y":[0,0]}},{"t":108.204,"s":[0.001,0],"i":{"x":[1,1],"y":[1,1]},"o":{"x":[0,0],"y":[0,0]}},{"t":108.9,"s":[0.093,0],"i":{"x":[1,1],"y":[1,1]},"o":{"x":[0,0],"y":[0,0]}},{"t":109.602,"s":[0,0],"i":{"x":[1,1],"y":[1,1]},"o":{"x":[0,0],"y":[0,0]}},{"t":240,"s":[0,0],"h":1}]}},"ip":0,"op":241,"st":0},{"ind":10,"ty":3,"ks":{"p":{"a":0,"k":[46,7]}},"ip":0,"op":241,"st":0}]},{"id":"17","layers":[{"ind":15,"ty":0,"parent":9,"ks":{"a":{"a":0,"k":[46,7]}},"w":228,"h":21,"ip":0,"op":241,"st":0,"refId":"13"},{"ind":16,"ty":4,"parent":9,"ks":{"o":{"a":1,"k":[{"t":0,"s":[0],"h":1},{"t":111,"s":[0],"h":1},{"t":111,"s":[100],"h":1},{"t":240,"s":[100],"h":1}]}},"ip":0,"op":241,"st":0,"shapes":[{"ty":"rc","p":{"a":0,"k":[50.05,7.7]},"r":{"a":0,"k":0},"s":{"a":0,"k":[120.1,19.4]}},{"ty":"fl","c":{"a":0,"k":[0,0,0]},"o":{"a":0,"k":100}}]},{"ind":9,"ty":3,"ks":{"p":{"a":0,"k":[46,7]}},"ip":0,"op":241,"st":0}]},{"id":"6","layers":[{"ind":5,"ty":4,"parent":4,"ks":{},"ip":0,"op":241,"st":0,"shapes":[{"ty":"rc","p":{"a":0,"k":[45.5,7]},"r":{"a":0,"k":0},"s":{"a":0,"k":[91,14]}},{"ty":"fl","c":{"a":0,"k":[0.008,0.204,0.145]},"o":{"a":0,"k":100}}]},{"ind":4,"ty":3,"parent":3,"ks":{"a":{"a":0,"k":[45.5,7]},"p":{"a":0,"k":[45.5,7]},"s":{"a":1,"k":[{"t":0,"s":[120,120],"i":{"x":[1,1],"y":[1,1]},"o":{"x":[0,0],"y":[0,0]}},{"t":45,"s":[120,120],"i":{"x":[0.741,0.741],"y":[0.482,0.482]},"o":{"x":[0.4,0.4],"y":[0,0]}},{"t":66.96,"s":[100,100],"i":{"x":[0.679,0.679],"y":[0.999,0.999]},"o":{"x":[0.347,0.347],"y":[0.693,0.693]}},{"t":77.94,"s":[105.01,105.01],"i":{"x":[0.733,0.733],"y":[0.466,0.466]},"o":{"x":[0.394,0.394],"y":[0.001,0.001]}},{"t":88.926,"s":[100,100],"i":{"x":[0.608,0.608],"y":[0.998,0.998]},"o":{"x":[0.27,0.27],"y":[0.539,0.539]}},{"t":94.422,"s":[101.25,101.25],"i":{"x":[0.564,0.564],"y":[0.129,0.129]},"o":{"x":[0.214,0.214],"y":[0.001,0.001]}},{"t":99.918,"s":[100,100],"i":{"x":[0.583,0.583],"y":[0.998,0.998]},"o":{"x":[0.236,0.236],"y":[0.473,0.473]}},{"t":102.678,"s":[100.32,100.32],"i":{"x":[0.533,0.533],"y":[0.07,0.07]},"o":{"x":[0.17,0.17],"y":[0.002,0.002]}},{"t":105.432,"s":[100,100],"i":{"x":[0.971,0.971],"y":[1,1]},"o":{"x":[0.539,0.539],"y":[1,1]}},{"t":106.818,"s":[100.08,100.08],"i":{"x":[0.454,0.454],"y":[0,0]},"o":{"x":[0.011,0.011],"y":[0,0]}},{"t":108.204,"s":[100,100],"i":{"x":[1,1],"y":[1,1]},"o":{"x":[0,0],"y":[0,0]}},{"t":108.9,"s":[100.02,100.02],"i":{"x":[1,1],"y":[1,1]},"o":{"x":[0,0],"y":[0,0]}},{"t":109.602,"s":[100,100],"i":{"x":[1,1],"y":[1,1]},"o":{"x":[0,0],"y":[0,0]}},{"t":240,"s":[100,100],"h":1}]}},"ip":0,"op":241,"st":0},{"ind":3,"ty":3,"ks":{"p":{"a":0,"k":[10,2]}},"ip":0,"op":241,"st":0}]},{"id":"20","layers":[{"ind":19,"ty":0,"td":1,"parent":2,"ks":{"a":{"a":0,"k":[46,7]}},"w":274,"h":28,"ip":0,"op":241,"st":0,"refId":"17"},{"ind":8,"ty":0,"tt":1,"parent":2,"ks":{"a":{"a":0,"k":[10,2]}},"w":111,"h":18,"ip":0,"op":241,"st":0,"refId":"6"},{"ind":2,"ty":3,"ks":{"p":{"a":0,"k":[10,2]}},"ip":0,"op":241,"st":0}]},{"id":"34","layers":[{"ind":33,"ty":4,"parent":32,"ks":{},"ip":0,"op":241,"st":0,"shapes":[{"ty":"rc","p":{"a":1,"k":[{"t":0,"s":[0,0],"i":{"x":[1,1],"y":[1,1]},"o":{"x":[0,0],"y":[0,0]}},{"t":45,"s":[0,0],"i":{"x":[0.741,0.741],"y":[0.482,0.482]},"o":{"x":[0.4,0.4],"y":[0,0]}},{"t":66.96,"s":[45.499,6.5],"i":{"x":[0.679,0.679],"y":[0.999,0.999]},"o":{"x":[0.347,0.347],"y":[0.693,0.693]}},{"t":77.94,"s":[34.112,4.873],"i":{"x":[0.733,0.733],"y":[0.466,0.466]},"o":{"x":[0.394,0.394],"y":[0.001,0.001]}},{"t":88.926,"s":[45.5,6.5],"i":{"x":[0.608,0.608],"y":[0.998,0.998]},"o":{"x":[0.27,0.27],"y":[0.539,0.539]}},{"t":94.422,"s":[42.647,6.092],"i":{"x":[0.564,0.564],"y":[0.129,0.129]},"o":{"x":[0.214,0.214],"y":[0.001,0.001]}},{"t":99.918,"s":[45.498,6.5],"i":{"x":[0.583,0.583],"y":[0.998,0.998]},"o":{"x":[0.236,0.236],"y":[0.473,0.473]}},{"t":102.678,"s":[44.783,6.398],"i":{"x":[0.533,0.533],"y":[0.07,0.07]},"o":{"x":[0.17,0.17],"y":[0.002,0.002]}},{"t":105.432,"s":[45.499,6.5],"i":{"x":[0.971,0.971],"y":[1,1]},"o":{"x":[0.539,0.539],"y":[1,1]}},{"t":106.818,"s":[45.319,6.474],"i":{"x":[0.454,0.454],"y":[0,0]},"o":{"x":[0.011,0.011],"y":[0,0]}},{"t":108.204,"s":[45.5,6.5],"i":{"x":[1,1],"y":[1,1]},"o":{"x":[0,0],"y":[0,0]}},{"t":108.9,"s":[45.454,6.493],"i":{"x":[1,1],"y":[1,1]},"o":{"x":[0,0],"y":[0,0]}},{"t":109.602,"s":[45.5,6.5],"i":{"x":[1,1],"y":[1,1]},"o":{"x":[0,0],"y":[0,0]}},{"t":240,"s":[45.5,6.5],"h":1}]},"r":{"a":0,"k":0},"s":{"a":1,"k":[{"t":0,"s":[0,0],"i":{"x":[1,1],"y":[1,1]},"o":{"x":[0,0],"y":[0,0]}},{"t":45,"s":[0,0],"i":{"x":[0.741,0.741],"y":[0.482,0.482]},"o":{"x":[0.4,0.4],"y":[0,0]}},{"t":66.96,"s":[90.998,13],"i":{"x":[0.679,0.679],"y":[0.999,0.999]},"o":{"x":[0.347,0.347],"y":[0.693,0.693]}},{"t":77.94,"s":[68.224,9.746],"i":{"x":[0.733,0.733],"y":[0.466,0.466]},"o":{"x":[0.394,0.394],"y":[0.001,0.001]}},{"t":88.926,"s":[90.999,13],"i":{"x":[0.608,0.608],"y":[0.998,0.998]},"o":{"x":[0.27,0.27],"y":[0.539,0.539]}},{"t":94.422,"s":[85.293,12.185],"i":{"x":[0.564,0.564],"y":[0.129,0.129]},"o":{"x":[0.214,0.214],"y":[0.001,0.001]}},{"t":99.918,"s":[90.996,12.999],"i":{"x":[0.583,0.583],"y":[0.998,0.998]},"o":{"x":[0.236,0.236],"y":[0.473,0.473]}},{"t":102.678,"s":[89.566,12.795],"i":{"x":[0.533,0.533],"y":[0.07,0.07]},"o":{"x":[0.17,0.17],"y":[0.002,0.002]}},{"t":105.432,"s":[90.997,13],"i":{"x":[0.971,0.971],"y":[1,1]},"o":{"x":[0.539,0.539],"y":[1,1]}},{"t":106.818,"s":[90.637,12.948],"i":{"x":[0.454,0.454],"y":[0,0]},"o":{"x":[0.011,0.011],"y":[0,0]}},{"t":108.204,"s":[90.999,13],"i":{"x":[1,1],"y":[1,1]},"o":{"x":[0,0],"y":[0,0]}},{"t":108.9,"s":[90.907,12.987],"i":{"x":[1,1],"y":[1,1]},"o":{"x":[0,0],"y":[0,0]}},{"t":109.602,"s":[91,13],"i":{"x":[1,1],"y":[1,1]},"o":{"x":[0,0],"y":[0,0]}},{"t":240,"s":[91,13],"h":1}]}},{"ty":"fl","c":{"a":0,"k":[0,0,0]},"o":{"a":0,"k":100}}]},{"ind":32,"ty":3,"parent":31,"ks":{},"ip":0,"op":241,"st":0},{"ind":31,"ty":3,"ks":{"p":{"a":0,"k":[46,7]}},"ip":0,"op":241,"st":0}]},{"id":"38","layers":[{"ind":36,"ty":0,"parent":30,"ks":{"a":{"a":0,"k":[46,7]}},"w":137,"h":20,"ip":0,"op":241,"st":0,"refId":"34"},{"ind":37,"ty":4,"parent":30,"ks":{"o":{"a":1,"k":[{"t":0,"s":[0],"h":1},{"t":111,"s":[0],"h":1},{"t":111,"s":[100],"h":1},{"t":240,"s":[100],"h":1}]}},"ip":0,"op":241,"st":0,"shapes":[{"ty":"rc","p":{"a":0,"k":[50.05,7.15]},"r":{"a":0,"k":0},"s":{"a":0,"k":[120.1,18.3]}},{"ty":"fl","c":{"a":0,"k":[0,0,0]},"o":{"a":0,"k":100}}]},{"ind":30,"ty":3,"ks":{"p":{"a":0,"k":[46,7]}},"ip":0,"op":241,"st":0}]},{"id":"27","layers":[{"ind":26,"ty":4,"parent":25,"ks":{},"ip":0,"op":241,"st":0,"shapes":[{"ty":"rc","p":{"a":0,"k":[45.5,6.5]},"r":{"a":0,"k":0},"s":{"a":0,"k":[91,13]}},{"ty":"fl","c":{"a":0,"k":[0.008,0.204,0.145]},"o":{"a":0,"k":100}}]},{"ind":25,"ty":3,"parent":24,"ks":{"a":{"a":0,"k":[45.5,6.5]},"p":{"a":0,"k":[45.5,6.5]},"s":{"a":1,"k":[{"t":0,"s":[120,120],"i":{"x":[1,1],"y":[1,1]},"o":{"x":[0,0],"y":[0,0]}},{"t":45,"s":[120,120],"i":{"x":[0.741,0.741],"y":[0.482,0.482]},"o":{"x":[0.4,0.4],"y":[0,0]}},{"t":66.96,"s":[100,100],"i":{"x":[0.679,0.679],"y":[0.999,0.999]},"o":{"x":[0.347,0.347],"y":[0.693,0.693]}},{"t":77.94,"s":[105.01,105.01],"i":{"x":[0.733,0.733],"y":[0.466,0.466]},"o":{"x":[0.394,0.394],"y":[0.001,0.001]}},{"t":88.926,"s":[100,100],"i":{"x":[0.608,0.608],"y":[0.998,0.998]},"o":{"x":[0.27,0.27],"y":[0.539,0.539]}},{"t":94.422,"s":[101.25,101.25],"i":{"x":[0.564,0.564],"y":[0.129,0.129]},"o":{"x":[0.214,0.214],"y":[0.001,0.001]}},{"t":99.918,"s":[100,100],"i":{"x":[0.583,0.583],"y":[0.998,0.998]},"o":{"x":[0.236,0.236],"y":[0.473,0.473]}},{"t":102.678,"s":[100.32,100.32],"i":{"x":[0.533,0.533],"y":[0.07,0.07]},"o":{"x":[0.17,0.17],"y":[0.002,0.002]}},{"t":105.432,"s":[100,100],"i":{"x":[0.971,0.971],"y":[1,1]},"o":{"x":[0.539,0.539],"y":[1,1]}},{"t":106.818,"s":[100.08,100.08],"i":{"x":[0.454,0.454],"y":[0,0]},"o":{"x":[0.011,0.011],"y":[0,0]}},{"t":108.204,"s":[100,100],"i":{"x":[1,1],"y":[1,1]},"o":{"x":[0,0],"y":[0,0]}},{"t":108.9,"s":[100.02,100.02],"i":{"x":[1,1],"y":[1,1]},"o":{"x":[0,0],"y":[0,0]}},{"t":109.602,"s":[100,100],"i":{"x":[1,1],"y":[1,1]},"o":{"x":[0,0],"y":[0,0]}},{"t":240,"s":[100,100],"h":1}]}},"ip":0,"op":241,"st":0},{"ind":24,"ty":3,"ks":{"p":{"a":0,"k":[10,2]}},"ip":0,"op":241,"st":0}]},{"id":"41","layers":[{"ind":40,"ty":0,"td":1,"parent":23,"ks":{"a":{"a":0,"k":[46,7]}},"w":183,"h":27,"ip":0,"op":241,"st":0,"refId":"38"},{"ind":29,"ty":0,"tt":1,"parent":23,"ks":{"a":{"a":0,"k":[10,2]}},"w":111,"h":17,"ip":0,"op":241,"st":0,"refId":"27"},{"ind":23,"ty":3,"ks":{"p":{"a":0,"k":[10,2]}},"ip":0,"op":241,"st":0}]},{"id":"51","layers":[{"ind":50,"ty":4,"parent":49,"ks":{},"ip":0,"op":241,"st":0,"shapes":[{"ty":"gr","it":[{"ty":"rc","p":{"a":0,"k":[50,50]},"r":{"a":0,"k":0},"s":{"a":0,"k":[102,102]}},{"ty":"fl","c":{"a":0,"k":[0,0,0,0]},"o":{"a":0,"k":0}},{"ty":"tr","o":{"a":0,"k":100}}]},{"ty":"gr","it":[{"ty":"rc","p":{"a":0,"k":[50,50]},"r":{"a":0,"k":0},"s":{"a":0,"k":[100,100]}},{"ty":"st","c":{"a":0,"k":[0.533,0.533,0.533]},"lc":1,"lj":1,"ml":10,"o":{"a":0,"k":100},"w":{"a":0,"k":2}},{"ty":"fl","c":{"a":0,"k":[0.102,0.102,0.102,0]},"o":{"a":0,"k":0}},{"ty":"tr","o":{"a":0,"k":100}}]}]},{"ind":49,"ty":3,"ks":{"p":{"a":0,"k":[1,1]}},"ip":0,"op":241,"st":0}]},{"id":"56","layers":[{"ind":55,"ty":4,"parent":54,"ks":{},"ip":0,"op":241,"st":0,"shapes":[{"ty":"gr","it":[{"ty":"rc","p":{"a":0,"k":[50,50]},"r":{"a":0,"k":0},"s":{"a":0,"k":[102,102]}},{"ty":"fl","c":{"a":0,"k":[0,0,0,0]},"o":{"a":0,"k":0}},{"ty":"tr","o":{"a":0,"k":100}}]},{"ty":"gr","it":[{"ty":"rc","p":{"a":0,"k":[50,50]},"r":{"a":0,"k":0},"s":{"a":0,"k":[100,100]}},{"ty":"st","c":{"a":0,"k":[0.533,0.533,0.533]},"lc":1,"lj":1,"ml":10,"o":{"a":0,"k":100},"w":{"a":0,"k":2}},{"ty":"fl","c":{"a":0,"k":[0.102,0.102,0.102,0]},"o":{"a":0,"k":0}},{"ty":"tr","o":{"a":0,"k":100}}]}]},{"ind":54,"ty":3,"ks":{"p":{"a":0,"k":[1,1]}},"ip":0,"op":241,"st":0}]},{"id":"66","layers":[{"ind":65,"ty":4,"parent":64,"ks":{},"ip":0,"op":241,"st":0,"shapes":[{"ty":"gr","it":[{"ty":"rc","p":{"a":0,"k":[50,50]},"r":{"a":0,"k":0},"s":{"a":0,"k":[102,102]}},{"ty":"fl","c":{"a":0,"k":[0,0,0,0]},"o":{"a":0,"k":0}},{"ty":"tr","o":{"a":0,"k":100}}]},{"ty":"gr","it":[{"ty":"rc","p":{"a":0,"k":[50,50]},"r":{"a":0,"k":0},"s":{"a":0,"k":[100,100]}},{"ty":"st","c":{"a":0,"k":[0.533,0.533,0.533]},"lc":1,"lj":1,"ml":10,"o":{"a":0,"k":100},"w":{"a":0,"k":2}},{"ty":"fl","c":{"a":0,"k":[0.102,0.102,0.102,0]},"o":{"a":0,"k":0}},{"ty":"tr","o":{"a":0,"k":100}}]}]},{"ind":64,"ty":3,"ks":{"p":{"a":0,"k":[1,1]}},"ip":0,"op":241,"st":0}]},{"id":"71","layers":[{"ind":70,"ty":4,"parent":69,"ks":{},"ip":0,"op":241,"st":0,"shapes":[{"ty":"gr","it":[{"ty":"rc","p":{"a":0,"k":[50,50]},"r":{"a":0,"k":0},"s":{"a":0,"k":[102,102]}},{"ty":"fl","c":{"a":0,"k":[0,0,0,0]},"o":{"a":0,"k":0}},{"ty":"tr","o":{"a":0,"k":100}}]},{"ty":"gr","it":[{"ty":"rc","p":{"a":0,"k":[50,50]},"r":{"a":0,"k":0},"s":{"a":0,"k":[100,100]}},{"ty":"st","c":{"a":0,"k":[0.533,0.533,0.533]},"lc":1,"lj":1,"ml":10,"o":{"a":0,"k":100},"w":{"a":0,"k":2}},{"ty":"fl","c":{"a":0,"k":[0.102,0.102,0.102,0]},"o":{"a":0,"k":0}},{"ty":"tr","o":{"a":0,"k":100}}]}]},{"ind":69,"ty":3,"ks":{"p":{"a":0,"k":[1,1]}},"ip":0,"op":241,"st":0}]}],"fr":60,"h":163,"ip":0,"layers":[{"ind":22,"ty":0,"parent":1,"ks":{"a":{"a":0,"k":[55.5,9]},"o":{"a":1,"k":[{"t":0,"s":[0],"h":1},{"t":45,"s":[0],"h":1},{"t":45,"s":[100],"h":1},{"t":240,"s":[100],"h":1}]},"p":{"a":0,"k":[232.5,39]},"r":{"a":0,"k":-45}},"w":121,"h":20,"ip":0,"op":241,"st":0,"refId":"20"},{"ind":43,"ty":0,"parent":1,"ks":{"a":{"a":0,"k":[55.5,8.5]},"o":{"a":1,"k":[{"t":0,"s":[0],"h":1},{"t":45,"s":[0],"h":1},{"t":45,"s":[100],"h":1},{"t":240,"s":[100],"h":1}]},"p":{"a":0,"k":[127.5,38.5]},"r":{"a":0,"k":45}},"w":121,"h":19,"ip":0,"op":241,"st":0,"refId":"41"},{"ind":46,"ty":4,"parent":45,"ks":{},"ip":0,"op":241,"st":0,"shapes":[{"ty":"rc","p":{"a":0,"k":[39,39]},"r":{"a":0,"k":0},"s":{"a":0,"k":[78,78]}},{"ty":"fl","c":{"a":0,"k":[0,1,0.706]},"o":{"a":0,"k":100}}]},{"ind":45,"ty":3,"parent":44,"ks":{"a":{"a":0,"k":[39,39]},"p":{"a":0,"k":[72,55]},"r":{"a":0,"k":45},"s":{"a":1,"k":[{"t":0,"s":[0,0],"i":{"x":[1,1],"y":[1,1]},"o":{"x":[0,0],"y":[0,0]}},{"t":36.6,"s":[0,0],"i":{"x":[0.2,0.2],"y":[1,1]},"o":{"x":[0,0],"y":[0,0]}},{"t":47.55,"s":[78,78],"i":{"x":[0.25,0.25],"y":[1,1]},"o":{"x":[0.2,0.2],"y":[0,0]}},{"t":80.4,"s":[65,65],"i":{"x":[1,1],"y":[1,1]},"o":{"x":[0,0],"y":[0,0]}},{"t":240,"s":[65,65],"h":1}]}},"ip":0,"op":241,"st":0},{"ind":48,"ty":4,"parent":47,"ks":{},"ip":0,"op":241,"st":0,"shapes":[{"ty":"rc","p":{"a":0,"k":[50,50]},"r":{"a":0,"k":0},"s":{"a":0,"k":[100,100]}},{"ty":"fl","c":{"a":0,"k":[0.008,0.204,0.145]},"o":{"a":0,"k":100}}]},{"ind":47,"ty":3,"parent":44,"ks":{"a":{"a":0,"k":[50,50]},"p":{"a":0,"k":[70.711,70.711]},"r":{"a":0,"k":45},"s":{"a":1,"k":[{"t":0,"s":[0,0],"i":{"x":[1,1],"y":[1,1]},"o":{"x":[0,0],"y":[0,0]}},{"t":27,"s":[0,0],"i":{"x":[0.2,0.2],"y":[1,1]},"o":{"x":[0,0],"y":[0,0]}},{"t":40.35,"s":[78,78],"i":{"x":[0.25,0.25],"y":[1,1]},"o":{"x":[0.2,0.2],"y":[0,0]}},{"t":80.4,"s":[65,65],"i":{"x":[1,1],"y":[1,1]},"o":{"x":[0,0],"y":[0,0]}},{"t":240,"s":[65,65],"h":1}]}},"ip":0,"op":241,"st":0},{"ind":53,"ty":0,"parent":44,"ks":{"a":{"a":0,"k":[51,51]},"o":{"a":1,"k":[{"t":0,"s":[100],"h":1},{"t":22.8,"s":[100],"i":{"x":1,"y":1},"o":{"x":0,"y":0}},{"t":53.4,"s":[0],"h":1},{"t":240,"s":[0],"h":1}]},"p":{"a":0,"k":[71,71]},"r":{"a":0,"k":45},"s":{"a":1,"k":[{"t":0,"s":[0,0],"i":{"x":[1,1],"y":[1,1]},"o":{"x":[0,0],"y":[0,0]}},{"t":10.2,"s":[0,0],"i":{"x":[0,0],"y":[1,1]},"o":{"x":[0.5,0.5],"y":[0,0]}},{"t":58.2,"s":[110,110],"i":{"x":[1,1],"y":[1,1]},"o":{"x":[0,0],"y":[0,0]}},{"t":240,"s":[110,110],"h":1}]}},"w":102,"h":102,"ip":0,"op":241,"st":0,"refId":"51"},{"ind":58,"ty":0,"parent":44,"ks":{"a":{"a":0,"k":[51,51]},"o":{"a":1,"k":[{"t":0,"s":[100],"h":1},{"t":12,"s":[100],"i":{"x":1,"y":1},"o":{"x":0,"y":0}},{"t":42.6,"s":[0],"h":1},{"t":240,"s":[0],"h":1}]},"p":{"a":0,"k":[70.711,70.711]},"r":{"a":0,"k":45},"s":{"a":1,"k":[{"t":0,"s":[0,0],"i":{"x":[0,0],"y":[1,1]},"o":{"x":[0.5,0.5],"y":[0,0]}},{"t":48,"s":[110,110],"i":{"x":[1,1],"y":[1,1]},"o":{"x":[0,0],"y":[0,0]}},{"t":240,"s":[110,110],"h":1}]}},"w":102,"h":102,"ip":0,"op":241,"st":0,"refId":"56"},{"ind":44,"ty":3,"parent":1,"ks":{"p":{"a":0,"k":[198,11]}},"ip":0,"op":241,"st":0},{"ind":61,"ty":4,"parent":60,"ks":{},"ip":0,"op":241,"st":0,"shapes":[{"ty":"rc","p":{"a":0,"k":[39,39]},"r":{"a":0,"k":0},"s":{"a":0,"k":[78,78]}},{"ty":"fl","c":{"a":0,"k":[0,1,0.706]},"o":{"a":0,"k":100}}]},{"ind":60,"ty":3,"parent":59,"ks":{"a":{"a":0,"k":[39,39]},"p":{"a":0,"k":[71,55]},"r":{"a":0,"k":45},"s":{"a":1,"k":[{"t":0,"s":[0,0],"i":{"x":[1,1],"y":[1,1]},"o":{"x":[0,0],"y":[0,0]}},{"t":36.6,"s":[0,0],"i":{"x":[0.2,0.2],"y":[1,1]},"o":{"x":[0,0],"y":[0,0]}},{"t":47.55,"s":[78,78],"i":{"x":[0.25,0.25],"y":[1,1]},"o":{"x":[0.2,0.2],"y":[0,0]}},{"t":80.4,"s":[65,65],"i":{"x":[1,1],"y":[1,1]},"o":{"x":[0,0],"y":[0,0]}},{"t":240,"s":[65,65],"h":1}]}},"ip":0,"op":241,"st":0},{"ind":63,"ty":4,"parent":62,"ks":{},"ip":0,"op":241,"st":0,"shapes":[{"ty":"rc","p":{"a":0,"k":[50,50]},"r":{"a":0,"k":0},"s":{"a":0,"k":[100,100]}},{"ty":"fl","c":{"a":0,"k":[0.008,0.204,0.145]},"o":{"a":0,"k":100}}]},{"ind":62,"ty":3,"parent":59,"ks":{"a":{"a":0,"k":[50,50]},"p":{"a":0,"k":[71,71]},"r":{"a":0,"k":45},"s":{"a":1,"k":[{"t":0,"s":[0,0],"i":{"x":[1,1],"y":[1,1]},"o":{"x":[0,0],"y":[0,0]}},{"t":27,"s":[0,0],"i":{"x":[0.2,0.2],"y":[1,1]},"o":{"x":[0,0],"y":[0,0]}},{"t":40.35,"s":[78,78],"i":{"x":[0.25,0.25],"y":[1,1]},"o":{"x":[0.2,0.2],"y":[0,0]}},{"t":80.4,"s":[65,65],"i":{"x":[1,1],"y":[1,1]},"o":{"x":[0,0],"y":[0,0]}},{"t":240,"s":[65,65],"h":1}]}},"ip":0,"op":241,"st":0},{"ind":68,"ty":0,"parent":59,"ks":{"a":{"a":0,"k":[51,51]},"o":{"a":1,"k":[{"t":0,"s":[100],"h":1},{"t":22.8,"s":[100],"i":{"x":1,"y":1},"o":{"x":0,"y":0}},{"t":53.4,"s":[0],"h":1},{"t":240,"s":[0],"h":1}]},"p":{"a":0,"k":[71,71]},"r":{"a":0,"k":45},"s":{"a":1,"k":[{"t":0,"s":[0,0],"i":{"x":[1,1],"y":[1,1]},"o":{"x":[0,0],"y":[0,0]}},{"t":10.2,"s":[0,0],"i":{"x":[0,0],"y":[1,1]},"o":{"x":[0.5,0.5],"y":[0,0]}},{"t":58.2,"s":[110,110],"i":{"x":[1,1],"y":[1,1]},"o":{"x":[0,0],"y":[0,0]}},{"t":240,"s":[110,110],"h":1}]}},"w":102,"h":102,"ip":0,"op":241,"st":0,"refId":"66"},{"ind":73,"ty":0,"parent":59,"ks":{"a":{"a":0,"k":[51,51]},"o":{"a":1,"k":[{"t":0,"s":[100],"h":1},{"t":12,"s":[100],"i":{"x":1,"y":1},"o":{"x":0,"y":0}},{"t":42.6,"s":[0],"h":1},{"t":240,"s":[0],"h":1}]},"p":{"a":0,"k":[70.711,70.711]},"r":{"a":0,"k":45},"s":{"a":1,"k":[{"t":0,"s":[0,0],"i":{"x":[0,0],"y":[1,1]},"o":{"x":[0.5,0.5],"y":[0,0]}},{"t":48,"s":[110,110],"i":{"x":[1,1],"y":[1,1]},"o":{"x":[0,0],"y":[0,0]}},{"t":240,"s":[110,110],"h":1}]}},"w":102,"h":102,"ip":0,"op":241,"st":0,"refId":"71"},{"ind":59,"ty":3,"parent":1,"ks":{"p":{"a":0,"k":[14,11]}},"ip":0,"op":241,"st":0},{"ind":1,"ty":3,"parent":0,"ks":{},"ip":0,"op":241,"st":0},{"ind":74,"ty":4,"parent":0,"ks":{},"ip":0,"op":241,"st":0,"shapes":[{"ty":"rc","p":{"a":0,"k":[176.5,81.5]},"r":{"a":0,"k":0},"s":{"a":0,"k":[353,163]}},{"ty":"fl","c":{"a":0,"k":[0,0,0]},"o":{"a":0,"k":100}}]},{"ind":0,"ty":3,"ks":{},"ip":0,"op":241,"st":0}],"meta":{"g":"https://jitter.video"},"op":240,"v":"5.7.4","w":353}